GCS_bucket_files_or_filenames/__init__.py
GCS_bucket_files_or_filenames/main.py
GCS_bucket_files_or_filenames-0.6.dist-info/METADATA
GCS_bucket_files_or_filenames-0.6.dist-info/WHEEL
GCS_bucket_files_or_filenames-0.6.dist-info/entry_points.txt
GCS_bucket_files_or_filenames-0.6.dist-info/top_level.txt
GCS_bucket_files_or_filenames-0.6.dist-info/RECORD
