Metadata-Version: 2.1
Name: GCS-bucket-files-or-filenames
Version: 0.6
